odoo10_addon_l10n_es_facturae-10.0.1.0.0.99.dev9-py2.7-nspkg.pth
odoo/addons/l10n_es_facturae/README.rst
odoo/addons/l10n_es_facturae/__init__.py
odoo/addons/l10n_es_facturae/__manifest__.py
odoo/addons/l10n_es_facturae/data/Facturaev3_2.xsd
odoo/addons/l10n_es_facturae/data/Facturaev3_2_1.xsd
odoo/addons/l10n_es_facturae/data/account_tax_template.xml
odoo/addons/l10n_es_facturae/data/log_counter.xml
odoo/addons/l10n_es_facturae/data/xmldsig-core-schema.xsd
odoo/addons/l10n_es_facturae/demo/integration_method.xml
odoo/addons/l10n_es_facturae/i18n/bg.po
odoo/addons/l10n_es_facturae/i18n/ca.po
odoo/addons/l10n_es_facturae/i18n/cs.po
odoo/addons/l10n_es_facturae/i18n/de.po
odoo/addons/l10n_es_facturae/i18n/es.po
odoo/addons/l10n_es_facturae/i18n/es_CO.po
odoo/addons/l10n_es_facturae/i18n/es_CR.po
odoo/addons/l10n_es_facturae/i18n/es_ES.po
odoo/addons/l10n_es_facturae/i18n/eu.po
odoo/addons/l10n_es_facturae/i18n/fr.po
odoo/addons/l10n_es_facturae/i18n/gl.po
odoo/addons/l10n_es_facturae/i18n/hr.po
odoo/addons/l10n_es_facturae/i18n/nl.po
odoo/addons/l10n_es_facturae/i18n/pl.po
odoo/addons/l10n_es_facturae/i18n/pt.po
odoo/addons/l10n_es_facturae/i18n/pt_BR.po
odoo/addons/l10n_es_facturae/i18n/ru.po
odoo/addons/l10n_es_facturae/i18n/sl.po
odoo/addons/l10n_es_facturae/i18n/sv.po
odoo/addons/l10n_es_facturae/i18n/tr.po
odoo/addons/l10n_es_facturae/i18n/vi.po
odoo/addons/l10n_es_facturae/models/__init__.py
odoo/addons/l10n_es_facturae/models/account_invoice.py
odoo/addons/l10n_es_facturae/models/account_invoice_integration.py
odoo/addons/l10n_es_facturae/models/account_invoice_integration_log.py
odoo/addons/l10n_es_facturae/models/account_invoice_integration_method.py
odoo/addons/l10n_es_facturae/models/account_tax.py
odoo/addons/l10n_es_facturae/models/account_tax_template.py
odoo/addons/l10n_es_facturae/models/payment_mode.py
odoo/addons/l10n_es_facturae/models/res_company.py
odoo/addons/l10n_es_facturae/models/res_currency.py
odoo10_addon_l10n_es_facturae-10.0.1.0.0.99.dev9.dist-info/DESCRIPTION.rst
odoo10_addon_l10n_es_facturae-10.0.1.0.0.99.dev9.dist-info/METADATA
odoo10_addon_l10n_es_facturae-10.0.1.0.0.99.dev9.dist-info/RECORD
odoo10_addon_l10n_es_facturae-10.0.1.0.0.99.dev9.dist-info/WHEEL
odoo10_addon_l10n_es_facturae-10.0.1.0.0.99.dev9.dist-info/metadata.json
odoo10_addon_l10n_es_facturae-10.0.1.0.0.99.dev9.dist-info/namespace_packages.txt
odoo10_addon_l10n_es_facturae-10.0.1.0.0.99.dev9.dist-info/top_level.txt
