Metadata-Version: 2.0
Name: odoo10-addon-l10n-es-facturae
Version: 10.0.1.0.0.99.dev9
Summary: Creación de Factura-e
Home-page: https://github.com/OCA/l10n-spain
Author: ASR-OSS, FactorLibre, Tecon, Comunitea, Tecnativa, Creu Blanca, Odoo Community Association (OCA)
Author-email: support@odoo-community.org
License: AGPL-3
Platform: UNKNOWN
Classifier: Programming Language :: Python
Classifier: Framework :: Odoo
Classifier: License :: OSI Approved :: GNU Affero General Public License v3
Requires-Python: ~=2.7
Requires-Dist: OpenSSL
Requires-Dist: odoo (<10.1dev,>=10.0)
Requires-Dist: odoo10-addon-account-banking-mandate
Requires-Dist: odoo10-addon-account-payment-partner
Requires-Dist: odoo10-addon-base-iso3166
Requires-Dist: odoo10-addon-l10n-es-partner
Requires-Dist: odoo10-addon-partner-firstname
Requires-Dist: odoo10-addon-report-qweb-parameter
Requires-Dist: odoo10-addon-report-xml
Requires-Dist: xmlsig
